[{"numExpertise":1,"codeAvertissement":"Purple","libAvertissement":"eleifend quam a","nomOperation":"dui vel","numPolice":"911630421-7","codeRefExterne":"881927530-9","initiales":"IV","refExpertise":"845675897-3","codeEtat":"cum","libEtat":"nam","codeEnjeu":"pulvinar","libEnjeu":"amet","dateJ45":"2021/11/22","dateJ60":"2021/07/06","dateJ90":"2021/05/20","numEcrac":"617919196-4","nbDommage":2},
{"numExpertise":2,"codeAvertissement":"Goldenrod","libAvertissement":"volutpat sapien","nomOperation":"sagittis nam","numPolice":"018386535-9","codeRefExterne":"657132406-7","initiales":"SR","refExpertise":"909941529-X","codeEtat":"donec","libEtat":"mattis","codeEnjeu":"volutpat","libEnjeu":"et","dateJ45":"2021/07/13","dateJ60":"2022/03/30","dateJ90":"2021/06/13","numEcrac":"985397186-0","nbDommage":3},
{"numExpertise":3,"codeAvertissement":"Puce","libAvertissement":"habitasse platea dictumst","nomOperation":"pede","numPolice":"318653770-3","codeRefExterne":"061187066-5","initiales":"JR","refExpertise":"336146618-0","codeEtat":"vitae","libEtat":"vestibulum","codeEnjeu":"risus","libEnjeu":"in","dateJ45":"2021/11/05","dateJ60":"2021/10/14","dateJ90":"2022/01/12","numEcrac":"706744937-5","nbDommage":5},
{"numExpertise":4,"codeAvertissement":"Orange","libAvertissement":"proin eu mi","nomOperation":"cras non velit","numPolice":"475162315-X","codeRefExterne":"577879723-0","initiales":"JR","refExpertise":"949249598-8","codeEtat":"tincidunt","libEtat":"morbi","codeEnjeu":"mauris","libEnjeu":"quis","dateJ45":"2021/12/08","dateJ60":"2022/01/15","dateJ90":"2022/01/09","numEcrac":"046723408-6","nbDommage":3},
{"numExpertise":5,"codeAvertissement":"Fuscia","libAvertissement":"morbi sem","nomOperation":"sed vestibulum","numPolice":"407917531-0","codeRefExterne":"904724766-3","initiales":"JR","refExpertise":"368433048-5","codeEtat":"morbi","libEtat":"sapien","codeEnjeu":"turpis","libEnjeu":"vulputate","dateJ45":"2022/04/01","dateJ60":"2021/07/24","dateJ90":"2021/10/11","numEcrac":"367257616-6","nbDommage":3},
{"numExpertise":6,"codeAvertissement":"Mauv","libAvertissement":"tellus nisi","nomOperation":"non","numPolice":"971749337-5","codeRefExterne":"526419108-5","initiales":"SR","refExpertise":"194095935-7","codeEtat":"lectus","libEtat":"pede","codeEnjeu":"ultrices","libEnjeu":"ut","dateJ45":"2021/11/18","dateJ60":"2021/12/04","dateJ90":"2021/09/05","numEcrac":"246347482-3","nbDommage":2},
{"numExpertise":7,"codeAvertissement":"Blue","libAvertissement":"fusce congue diam","nomOperation":"eget tincidunt eget","numPolice":"834595607-6","codeRefExterne":"272066221-6","initiales":"III","refExpertise":"381984663-8","codeEtat":"nibh","libEtat":"ac","codeEnjeu":"rhoncus","libEnjeu":"semper","dateJ45":"2022/02/20","dateJ60":"2021/08/22","dateJ90":"2021/11/17","numEcrac":"347608059-5","nbDommage":2},
{"numExpertise":8,"codeAvertissement":"Orange","libAvertissement":"vulputate ut ultrices","nomOperation":"dolor","numPolice":"891046018-0","codeRefExterne":"325293836-7","initiales":"IV","refExpertise":"914242380-5","codeEtat":"ac","libEtat":"augue","codeEnjeu":"nulla","libEnjeu":"lacinia","dateJ45":"2021/11/18","dateJ60":"2021/04/10","dateJ90":"2021/05/07","numEcrac":"085351553-0","nbDommage":1},
{"numExpertise":9,"codeAvertissement":"Blue","libAvertissement":"aliquam non mauris","nomOperation":"est lacinia nisi","numPolice":"570938302-3","codeRefExterne":"610659913-0","initiales":"IV","refExpertise":"346487589-X","codeEtat":"nec","libEtat":"vestibulum","codeEnjeu":"aliquet","libEnjeu":"semper","dateJ45":"2022/02/11","dateJ60":"2021/07/14","dateJ90":"2021/04/09","numEcrac":"375403926-1","nbDommage":1},
{"numExpertise":10,"codeAvertissement":"Puce","libAvertissement":"interdum venenatis turpis","nomOperation":"diam in","numPolice":"979823897-4","codeRefExterne":"503782983-6","initiales":"SR","refExpertise":"285850909-3","codeEtat":"tortor","libEtat":"in","codeEnjeu":"hac","libEnjeu":"nulla","dateJ45":"2021/06/23","dateJ60":"2021/09/08","dateJ90":"2021/07/02","numEcrac":"685270992-2","nbDommage":2},
{"numExpertise":11,"codeAvertissement":"Teal","libAvertissement":"donec dapibus duis","nomOperation":"sit amet","numPolice":"875188873-4","codeRefExterne":"394473567-6","initiales":"SR","refExpertise":"575184065-8","codeEtat":"consequat","libEtat":"vivamus","codeEnjeu":"metus","libEnjeu":"sit","dateJ45":"2022/02/11","dateJ60":"2022/01/16","dateJ90":"2021/07/20","numEcrac":"438503199-1","nbDommage":3},
{"numExpertise":12,"codeAvertissement":"Puce","libAvertissement":"etiam justo etiam","nomOperation":"iaculis","numPolice":"422716008-1","codeRefExterne":"153616601-4","initiales":"II","refExpertise":"704463237-8","codeEtat":"id","libEtat":"suspendisse","codeEnjeu":"sapien","libEnjeu":"vel","dateJ45":"2021/10/16","dateJ60":"2021/06/14","dateJ90":"2022/03/11","numEcrac":"280664908-0","nbDommage":5},
{"numExpertise":13,"codeAvertissement":"Blue","libAvertissement":"quam sollicitudin vitae","nomOperation":"erat eros viverra","numPolice":"020708363-0","codeRefExterne":"649100221-7","initiales":"III","refExpertise":"502548971-7","codeEtat":"lacinia","libEtat":"quisque","codeEnjeu":"ultrices","libEnjeu":"odio","dateJ45":"2021/04/10","dateJ60":"2021/10/09","dateJ90":"2022/02/04","numEcrac":"530066078-7","nbDommage":1},
{"numExpertise":14,"codeAvertissement":"Red","libAvertissement":"ut nulla sed","nomOperation":"in leo maecenas","numPolice":"967013594-X","codeRefExterne":"811605536-4","initiales":"IV","refExpertise":"363578581-4","codeEtat":"vivamus","libEtat":"nam","codeEnjeu":"aenean","libEnjeu":"nisl","dateJ45":"2021/11/12","dateJ60":"2022/02/01","dateJ90":"2021/09/09","numEcrac":"108612100-7","nbDommage":5},
{"numExpertise":15,"codeAvertissement":"Crimson","libAvertissement":"eget rutrum","nomOperation":"diam erat fermentum","numPolice":"820417790-9","codeRefExterne":"692410683-8","initiales":"IV","refExpertise":"472728031-0","codeEtat":"lorem","libEtat":"urna","codeEnjeu":"elementum","libEnjeu":"euismod","dateJ45":"2021/06/08","dateJ60":"2021/12/09","dateJ90":"2021/06/18","numEcrac":"912278947-2","nbDommage":4},
{"numExpertise":16,"codeAvertissement":"Teal","libAvertissement":"donec odio","nomOperation":"donec semper sapien","numPolice":"234350511-X","codeRefExterne":"980420437-1","initiales":"SR","refExpertise":"756422634-X","codeEtat":"nullam","libEtat":"maecenas","codeEnjeu":"tempus","libEnjeu":"tortor","dateJ45":"2021/08/25","dateJ60":"2021/12/23","dateJ90":"2022/03/01","numEcrac":"202279403-6","nbDommage":1},
{"numExpertise":17,"codeAvertissement":"Orange","libAvertissement":"rhoncus dui","nomOperation":"convallis","numPolice":"110579319-2","codeRefExterne":"264056126-X","initiales":"II","refExpertise":"626148652-2","codeEtat":"proin","libEtat":"ipsum","codeEnjeu":"eu","libEnjeu":"tortor","dateJ45":"2021/08/03","dateJ60":"2021/08/19","dateJ90":"2021/05/22","numEcrac":"391627141-5","nbDommage":1},
{"numExpertise":18,"codeAvertissement":"Yellow","libAvertissement":"aliquam non mauris","nomOperation":"mauris sit","numPolice":"855869002-2","codeRefExterne":"182396789-2","initiales":"SR","refExpertise":"517296921-7","codeEtat":"suscipit","libEtat":"primis","codeEnjeu":"quis","libEnjeu":"mauris","dateJ45":"2021/08/11","dateJ60":"2021/11/16","dateJ90":"2021/06/04","numEcrac":"593578878-0","nbDommage":1},
{"numExpertise":19,"codeAvertissement":"Puce","libAvertissement":"elit ac nulla","nomOperation":"tortor risus","numPolice":"614628058-5","codeRefExterne":"868846589-4","initiales":"IV","refExpertise":"019233079-9","codeEtat":"enim","libEtat":"sed","codeEnjeu":"sit","libEnjeu":"iaculis","dateJ45":"2021/05/26","dateJ60":"2022/03/18","dateJ90":"2022/02/12","numEcrac":"018455551-5","nbDommage":3},
{"numExpertise":20,"codeAvertissement":"Goldenrod","libAvertissement":"ipsum primis","nomOperation":"duis at","numPolice":"387608346-X","codeRefExterne":"448981617-0","initiales":"JR","refExpertise":"856118238-5","codeEtat":"id","libEtat":"quis","codeEnjeu":"pede","libEnjeu":"aliquet","dateJ45":"2021/12/27","dateJ60":"2021/08/07","dateJ90":"2021/07/23","numEcrac":"473292166-3","nbDommage":5},
{"numExpertise":21,"codeAvertissement":"Indigo","libAvertissement":"ipsum primis","nomOperation":"vitae consectetuer eget","numPolice":"834119917-3","codeRefExterne":"519551493-3","initiales":"IV","refExpertise":"096085634-X","codeEtat":"vel","libEtat":"scelerisque","codeEnjeu":"luctus","libEnjeu":"est","dateJ45":"2021/04/22","dateJ60":"2021/06/23","dateJ90":"2021/05/06","numEcrac":"995754090-4","nbDommage":4},
{"numExpertise":22,"codeAvertissement":"Violet","libAvertissement":"interdum eu tincidunt","nomOperation":"sapien","numPolice":"905700628-6","codeRefExterne":"995397708-9","initiales":"SR","refExpertise":"447209037-6","codeEtat":"quis","libEtat":"pulvinar","codeEnjeu":"vulputate","libEnjeu":"est","dateJ45":"2021/09/26","dateJ60":"2021/04/10","dateJ90":"2021/12/29","numEcrac":"460866778-5","nbDommage":2},
{"numExpertise":23,"codeAvertissement":"Turquoise","libAvertissement":"dolor sit","nomOperation":"pellentesque ultrices","numPolice":"227115435-9","codeRefExterne":"256731288-9","initiales":"IV","refExpertise":"520546253-1","codeEtat":"convallis","libEtat":"morbi","codeEnjeu":"eros","libEnjeu":"vestibulum","dateJ45":"2021/05/29","dateJ60":"2021/09/28","dateJ90":"2021/06/23","numEcrac":"338923086-6","nbDommage":2},
{"numExpertise":24,"codeAvertissement":"Pink","libAvertissement":"etiam faucibus cursus","nomOperation":"pede","numPolice":"988824565-1","codeRefExterne":"119101221-2","initiales":"SR","refExpertise":"209534296-8","codeEtat":"morbi","libEtat":"vestibulum","codeEnjeu":"eget","libEnjeu":"ultrices","dateJ45":"2021/06/14","dateJ60":"2021/11/02","dateJ90":"2021/07/28","numEcrac":"028074580-X","nbDommage":4}]
